platzi/__init__.py
platzi/async_api.py
platzi/cache.py
platzi/cli.py
platzi/collectors.py
platzi/constants.py
platzi/helpers.py
platzi/logger.py
platzi/m3u8.py
platzi/models.py
platzi/utils.py
platzi-0.7.3.dist-info/METADATA
platzi-0.7.3.dist-info/WHEEL
platzi-0.7.3.dist-info/entry_points.txt
platzi-0.7.3.dist-info/licenses/LICENCE
platzi-0.7.3.dist-info/RECORD
