Metadata-Version: 2.4
Name: platzi
Version: 0.7.3
Summary: Download your courses from platzi
License: MIT
License-File: LICENCE
Keywords: Platzi,downloader,courses
Author: ivansaul
Author-email: ivansaul@no-reply.com
Requires-Python: >=3.10,<4.0
Classifier: License :: OSI Approved :: MIT License
Classifier: Operating System :: OS Independent
Classifier: Programming Language :: Python :: 3
Classifier: Programming Language :: Python :: 3.10
Classifier: Programming Language :: Python :: 3.11
Classifier: Programming Language :: Python :: 3.12
Classifier: Programming Language :: Python :: 3.13
Classifier: Programming Language :: Python :: 3.14
Requires-Dist: aiofiles (>=25.1.0,<26.0.0)
Requires-Dist: platformdirs (>=4.3.6,<5.0.0)
Requires-Dist: pydantic (>=2.9.2,<3.0.0)
Requires-Dist: pyhumps (>=3.8.0,<4.0.0)
Requires-Dist: pytest-playwright (>=0.5.2,<0.6.0)
Requires-Dist: rnet (>=2.4.2,<3.0.0)
Requires-Dist: tqdm (>=4.67.0,<5.0.0)
Requires-Dist: typer (>=0.19.2,<0.20.0)
Requires-Dist: unidecode (>=1.3.8,<2.0.0)
Project-URL: Homepage, https://github.com/ivansaul/platzi-downloader
Project-URL: Repository, https://github.com/ivansaul/platzi-downloader
